sparrow_mlpipes/__init__.py
sparrow_mlpipes/constants.py
sparrow_mlpipes/element.py
sparrow_mlpipes/exceptions.py
sparrow_mlpipes/initialize.py
sparrow_mlpipes/meta.py
sparrow_mlpipes/pipeline.py
sparrow_mlpipes/pyds.py
sparrow_mlpipes/bins/__init__.py
sparrow_mlpipes/bins/nvinfer.py
sparrow_mlpipes/bins/nvinferserver.py
sparrow_mlpipes/bins/nvtracker.py
sparrow_mlpipes/bins/sink.py
sparrow_mlpipes/bins/source.py
sparrow_mlpipes/bins/visualization.py
sparrow_mlpipes-0.4.7.dist-info/LICENSE
sparrow_mlpipes-0.4.7.dist-info/METADATA
sparrow_mlpipes-0.4.7.dist-info/WHEEL
sparrow_mlpipes-0.4.7.dist-info/top_level.txt
sparrow_mlpipes-0.4.7.dist-info/RECORD
